HISTORY.rst
LICENSE.txt
MANIFEST.in
README.rst
setup.py
buck.pprint.egg-info/PKG-INFO
buck.pprint.egg-info/SOURCES.txt
buck.pprint.egg-info/dependency_links.txt
buck.pprint.egg-info/namespace_packages.txt
buck.pprint.egg-info/top_level.txt
buck/pprint/__init__.py
buck/pprint/version.py