Metadata-Version: 1.0
Name: buck.pprint
Version: 0.0
Summary: A fork of the cpython's pprint which gives standard indentation.
Home-page: https://github.com/bukzor/buck.pprint
Author: Buck Golemon
Author-email: buck.golemon@gmail.com
License: LICENSE.txt
Platform: UNKNOWN
Classifier: Development Status :: 3 - Alpha
Classifier: Environment :: Console
Classifier: Intended Audience :: Developers
Classifier: License :: OSI Approved :: MIT License
Classifier: Natural Language :: English
Classifier: Operating System :: OS Independent
Classifier: Topic :: Software Development :: Code Generators
